flask_collect/__init__.py
flask_collect/collect.py
flask_collect/version.py
flask_collect/storage/__init__.py
flask_collect/storage/base.py
flask_collect/storage/file.py
flask_collect/storage/link.py
flask_collect/storage/test.py
tests/__init__.py
tests/test_collect.py
Flask_Collect_Invenio-1.4.0.dist-info/LICENSE
Flask_Collect_Invenio-1.4.0.dist-info/METADATA
Flask_Collect_Invenio-1.4.0.dist-info/WHEEL
Flask_Collect_Invenio-1.4.0.dist-info/top_level.txt
Flask_Collect_Invenio-1.4.0.dist-info/RECORD
