Metadata-Version: 2.1
Name: Flask-Collect-Invenio
Version: 1.4.0
Summary: Flask-Collect-Invenio -- Collect static files in Flask application 
Home-page: http://github.com/inveniosoftware/Flask-Collect-Invenio
Author: Kirill Klenov
Author-email: horneds@gmail.com
License: BSD
Keywords: flask,static,deploy
Platform: any
Classifier: Development Status :: 4 - Beta
Classifier: Intended Audience :: Developers
Classifier: License :: OSI Approved :: BSD License
Classifier: Operating System :: OS Independent
Classifier: Programming Language :: Python :: 3
Classifier: Programming Language :: Python
Classifier: Framework :: Flask
Classifier: Topic :: Software Development :: Libraries :: Python Modules
Classifier: Topic :: Utilities
Requires-Dist: Flask (>=0.10.1)
Provides-Extra: all
Requires-Dist: Sphinx (>=3) ; extra == 'all'
Requires-Dist: black (>=21.9b0) ; extra == 'all'
Requires-Dist: check-manifest (>=0.42) ; extra == 'all'
Requires-Dist: coverage (<6,>=5.3) ; extra == 'all'
Requires-Dist: pytest (<7,>=6) ; extra == 'all'
Requires-Dist: pytest-cov (>=2.10.1) ; extra == 'all'
Requires-Dist: pytest-flask (>=1.0.0) ; extra == 'all'
Requires-Dist: pytest-isort (>=1.2.0) ; extra == 'all'
Requires-Dist: pytest-pycodestyle (>=2.2.0) ; extra == 'all'
Requires-Dist: pytest-pydocstyle (>=2.2.0) ; extra == 'all'
Provides-Extra: docs
Requires-Dist: Sphinx (>=3) ; extra == 'docs'
Provides-Extra: tests
Requires-Dist: black (>=21.9b0) ; extra == 'tests'
Requires-Dist: check-manifest (>=0.42) ; extra == 'tests'
Requires-Dist: coverage (<6,>=5.3) ; extra == 'tests'
Requires-Dist: pytest (<7,>=6) ; extra == 'tests'
Requires-Dist: pytest-cov (>=2.10.1) ; extra == 'tests'
Requires-Dist: pytest-flask (>=1.0.0) ; extra == 'tests'
Requires-Dist: pytest-isort (>=1.2.0) ; extra == 'tests'
Requires-Dist: pytest-pycodestyle (>=2.2.0) ; extra == 'tests'
Requires-Dist: pytest-pydocstyle (>=2.2.0) ; extra == 'tests'
